PEM4Fe/__init__.py
PEM4Fe/config.py
PEM4Fe/data_processing.py
PEM4Fe/fitting.py
PEM4Fe/main.py
PEM4Fe/output.py
PEM4Fe/peak_detection.py
PEM4Fe-1.0.2.dist-info/LICENSE
PEM4Fe-1.0.2.dist-info/METADATA
PEM4Fe-1.0.2.dist-info/WHEEL
PEM4Fe-1.0.2.dist-info/entry_points.txt
PEM4Fe-1.0.2.dist-info/top_level.txt
PEM4Fe-1.0.2.dist-info/RECORD
