Metadata-Version: 2.1
Name: PEM4Fe
Version: 1.0.2
Summary: A tool for data processing and peak detection for PEM
Home-page: https://github.com/HUSKYzjh/PEM4Fe
Author: Jiahui Zhai
Author-email: 19720212203881@stu.xmu.edu.cn
Classifier: Programming Language :: Python :: 3
Classifier: License :: OSI Approved :: MIT License
Classifier: Operating System :: OS Independent
Requires-Python: >=3.6
License-File: LICENSE
Requires-Dist: matplotlib
Requires-Dist: numpy
Requires-Dist: pandas
Requires-Dist: pyyaml
Requires-Dist: scipy
